<?xml version="1.0" encoding="ISO-8859-1"?>

<charmlist xmlns:xsi="http://www.w3.org/2001/XMLSchema-instance" xsi:noNamespaceSchemaLocation="ComplexCharms.xsd">
   <charm id="Dragon-Blooded.Language-LearningRitual" exalt="Dragon-Blooded" group="Linguistics">
    <prerequisite>
      <essence value="1"/>
      <trait id="Linguistics" value="2"/>
    </prerequisite>
    <cost>
      
        <essence cost="5"/>
        <willpower cost="1"/>
      
    </cost>
    <duration amount="1" unit="week"/>
    <charmtype type="Simple"/>
    <charmAttribute attribute="Stackable" visualize="true"/>
    <source source="DragonBlooded2nd"/>
  </charm>
  <charm id="Dragon-Blooded.CipherMissive" exalt="Dragon-Blooded" group="Linguistics">
    <prerequisite>
      <essence value="1"/>
      <trait id="Linguistics" value="2"/>
      <charmReference id="Dragon-Blooded.Language-LearningRitual"/>
    </prerequisite>
    <cost>
      
        <essence cost="3"/>
      
    </cost>
    <duration duration="Instant"/>
    <charmtype type="Simple"/>
    <charmAttribute attribute="Combo-OK" visualize="true"/>
    <source source="DragonBlooded2nd"/>
  </charm>
    <charm id="Dragon-Blooded.CraftIcon" exalt="Dragon-Blooded" group="Linguistics">
    <prerequisite>
      <essence value="3"/>
      <trait id="Linguistics" value="3"/>
      <charmReference id="Dragon-Blooded.CipherMissive"/>
    </prerequisite>
    <cost>
      
        <essence cost="2"/>
      
    </cost>
    <duration duration="Instant"/>
    <charmtype type="Simple"/>
    <charmAttribute attribute="Combo-OK" visualize="true"/>
    <source source="DragonBlooded2nd"/>
  </charm>
    <charm id="Dragon-Blooded.ThousandTonguesMeditation" exalt="Dragon-Blooded" group="Linguistics">
    <prerequisite>
      <essence value="2"/>
      <trait id="Linguistics" value="3"/>
      <charmReference id="Dragon-Blooded.Language-LearningRitual"/>
    </prerequisite>
    <cost>
      
        <essence cost="4"/>
      
    </cost>
    <duration amount="1" unit="scene"/>
    <charmtype type="Simple"/>
    <charmAttribute attribute="Combo-OK" visualize="true"/>
    <charmAttribute attribute="Social" visualize="true"/>
    <source source="DragonBlooded2nd"/>
  </charm>
    <charm id="Dragon-Blooded.PoisonedTongueTechnique" exalt="Dragon-Blooded" group="Linguistics">
    <prerequisite>
      <essence value="3"/>
      <trait id="Linguistics" value="3"/>
      <charmAttributeRequirement attribute="ExcellencyLinguistics" count="1"/>
    </prerequisite>
    <cost>
      
        <essence cost="2"/>
        <willpower cost="1"/>
      
    </cost>
    <duration duration="Concentration"/>
    <charmtype type="Simple"/>
    <charmAttribute attribute="Combo-OK" visualize="true"/>
    <charmAttribute attribute="Social" visualize="true"/>
    <charmAttribute attribute="War" visualize="true"/>
    <source source="DragonBlooded2nd"/>
  </charm>
   <charm id="Dragon-Blooded.VoiceMastery" exalt="Dragon-Blooded" group="Linguistics">
    <prerequisite>
      <essence value="3"/>
      <trait id="Linguistics" value="4"/>
       <charmReference id="Dragon-Blooded.PoisonedTongueTechnique"/>
    </prerequisite>
    <cost>
      
        <essence cost="5" text="or more"/>
      
    </cost>
    <duration amount="1" unit="scene"/>
    <charmtype type="Simple"/>
    <charmAttribute attribute="Combo-OK" visualize="true"/>
    <charmAttribute attribute="Social" visualize="true"/>
    <source source="DragonBlooded2nd"/>
  </charm>
   <charm id="Dragon-Blooded.Wind-CarriedWordsTechnique" exalt="Dragon-Blooded" group="Linguistics">
    <prerequisite>
      <essence value="2"/>
      <trait id="Linguistics" value="3"/>
    </prerequisite>
    <cost>
      
        <essence cost="1" text="per message, plus distance"/>
      
    </cost>
    <duration duration="Instant"/>
    <charmtype type="Simple"/>
    <charmAttribute attribute="Combo-OK" visualize="true"/>
    <source source="DragonBlooded2nd"/>
  </charm>
  <charm id="Dragon-Blooded.VoicesWind" exalt="Dragon-Blooded" group="Linguistics">
    <prerequisite>
      <essence value="3"/>
      <trait id="Linguistics" value="4"/>
      <charmReference id="Dragon-Blooded.Wind-CarriedWordsTechnique"/>
    </prerequisite>
    <cost>
      
        <essence cost="3" text="or more"/>
      
    </cost>
    <duration amount="1" unit="minute"/>
    <charmtype type="Simple"/>
    <charmAttribute attribute="Combo-OK" visualize="true"/>
    <charmAttribute attribute="Social" visualize="true"/>
    <source source="DragonBlooded2nd"/>
  </charm>
  
   <charm id="Dragon-Blooded.SpeechWithoutWords" exalt="Dragon-Blooded" group="Linguistics">
    <prerequisite>
      <essence value="3"/>
      <trait id="Linguistics" value="3"/>
      <charmReference id="Dragon-Blooded.CipherMissive"/>
      <charmReference id="Dragon-Blooded.VoicesWind"/>
    </prerequisite>
    <cost>
      
        <essence cost="2" text="+1m per ally"/>
      
    </cost>
    <duration amount="1" unit="scene"/>
    <charmtype type="Simple"/>
    <charmAttribute attribute="Combo-Basic" visualize="true"/>
    <source source="DragonBlooded2nd"/>
  </charm>
  
   <charm id="Dragon-Blooded.WithOneMind" exalt="Dragon-Blooded" group="Linguistics">
    <prerequisite>
      <essence value="2"/>
      <trait id="Linguistics" value="5"/>
      <charmReference id="Dragon-Blooded.VoiceMastery"/>
      <charmReference id="Dragon-Blooded.VoicesWind"/>
    </prerequisite>
    <cost>
      
        <essence cost="2" text="per dot of increase"/>
      
    </cost>
    <duration amount="1" unit="scene"/>
    <charmtype type="Simple"/>
    <charmAttribute attribute="Combo-Basic" visualize="true"/>
    <charmAttribute attribute="Dynasty" visualize="true"/>
    <charmAttribute attribute="War" visualize="true"/>
    <source source="DragonBlooded2nd"/>
  </charm>
</charmlist>
