<?xml version="1.0"?>
<!DOCTYPE plugin-fragment PUBLIC "-//JPF//Java Plug-in Manifest 0.6"
"http://jpf.sourceforge.net/plugin_0_6.dtd">
<plugin-fragment id="net.sf.anathema.character.inkmonkeys" version="1.10" plugin-id="net.sf.anathema.character" plugin-version="1.03">
     <runtime>
          <library id="InkMonkeys" path="./" type="code">
               <export prefix="*" />
          </library>
          <library id="InkMonkeysResources" path="./" type="resources">
               <export prefix="*" />
          </library>
     </runtime>
     <extension plugin-id="net.sf.anathema.core" point-id="AnathemaResources" id="InkMonkeysResources">
          <parameter id="bundle" value="inkMonkeys" />
          <parameter id="bundle" value="Pages_inkMonkeys" />
          <parameter id="bundle" value="Charms_inkMonkeys" />
     </extension>
</plugin-fragment>
